autocert/__init__.py
autocert/acme.py
autocert/autocert.py
autocert/cache.py
autocert/jwk.py
autocert/jws.py
autocert/keys.py
autocert/manager.py
autocert/rfc4648.py
autocert/wsgi.py
autocert-0.0.7.dist-info/LICENSE
autocert-0.0.7.dist-info/METADATA
autocert-0.0.7.dist-info/WHEEL
autocert-0.0.7.dist-info/top_level.txt
autocert-0.0.7.dist-info/RECORD
