Metadata-Version: 2.1
Name: autocert
Version: 0.0.7
Summary: Automatic TLS cert issuance and renewal for Python web apps
Home-page: https://github.com/theandrew168/autocert
Author: Andrew Dailey
License: UNKNOWN
Platform: UNKNOWN
Classifier: License :: OSI Approved :: MIT License
Classifier: Operating System :: OS Independent
Classifier: Programming Language :: Python :: 3.7
Classifier: Programming Language :: Python :: 3.8
Classifier: Programming Language :: Python :: 3.9
Classifier: Programming Language :: Python :: 3.10
Classifier: Programming Language :: Python :: Implementation :: CPython
Classifier: Topic :: Internet :: WWW/HTTP :: HTTP Servers
Classifier: Topic :: System :: Networking
Requires-Python: >=3.7
Requires-Dist: appdirs
Requires-Dist: cryptography
Requires-Dist: requests
